pandoc_filter_lc/pandoc.py
pandoc_filter_lc-0.1.dist-info/LICENSE
pandoc_filter_lc-0.1.dist-info/METADATA
pandoc_filter_lc-0.1.dist-info/WHEEL
pandoc_filter_lc-0.1.dist-info/top_level.txt
pandoc_filter_lc-0.1.dist-info/RECORD
