Metadata-Version: 2.1
Name: pandoc-filter-lc
Version: 0.1
Summary: a pandoc filter for mermaid
Author: Clovis Heaulier
Author-email: clovis.heaulier@gmail.com
License: MIT
Keywords: pandoc mermaid
Requires-Python: >=2.7
License-File: LICENSE
Requires-Dist: numpy >=1.19
Requires-Dist: ply
Requires-Dist: Pillow
Requires-Dist: datetime
Requires-Dist: argparse
